{
  "title": "Home-Pin-Cocos",
  "packageName": "org.cocos2d.demo",
  "startScene": "0f514cb1-6978-4f46-88f7-c5c7b45d08a9",
  "excludeScenes": [],
  "orientation": {
    "landscapeRight": false,
    "landscapeLeft": false,
    "portrait": true,
    "upsideDown": false
  },
  "webOrientation": "auto",
  "inlineSpriteFrames": false,
  "inlineSpriteFrames_native": true,
  "mainCompressionType": "default",
  "mainIsRemote": false,
  "optimizeHotUpdate": false,
  "md5Cache": false,
  "nativeMd5Cache": false,
  "encryptJs": true,
  "xxteaKey": "b9a13117-6e8c-4b",
  "zipCompressJs": true,
  "fb-instant-games": {},
  "android": {
    "packageName": "com.gamee.cocos.homepin",
    "REMOTE_SERVER_ROOT": ""
  },
  "ios": {
    "packageName": "org.cocos2d.demo",
    "REMOTE_SERVER_ROOT": "",
    "ios_enable_jit": true
  },
  "mac": {
    "packageName": "org.cocos2d.demo",
    "REMOTE_SERVER_ROOT": "",
    "width": 1280,
    "height": 720
  },
  "win32": {
    "REMOTE_SERVER_ROOT": "",
    "width": 1280,
    "height": 720
  },
  "android-instant": {
    "packageName": "org.cocos2d.demo",
    "REMOTE_SERVER_ROOT": "http://192.168.0.100:7456/preview-android-instant/",
    "pathPattern": "",
    "scheme": "https",
    "host": "",
    "skipRecord": false,
    "recordPath": ""
  },
  "appBundle": false,
  "agreements": {
    "20200831115453": false,
    "20200831115431": false,
    "20220901093311": false
  },
  "includeAnySDK": false
}
